[
  {
    "inputs": [
      {
        "internalType": "address",
        "name": "token",
        "type": "address"
      }
    ],
    "stateMutability": "nonpayable",
    "type": "constructor"
  },
  {
    "anonymous": false,
    "inputs": [
      {
        "indexed": true,
        "internalType": "address",
        "name": "user",
        "type": "address"
      },
      {
        "indexed": false,
        "internalType": "uint256",
        "name": "amount",
        "type": "uint256"
      },
      {
        "indexed": true,
        "internalType": "bytes32",
        "name": "vegaPublicKey",
        "type": "bytes32"
      }
    ],
    "name": "StakeDeposited",
    "type": "event"
  },
  {
    "anonymous": false,
    "inputs": [
      {
        "indexed": true,
        "internalType": "address",
        "name": "user",
        "type": "address"
      },
      {
        "indexed": false,
        "internalType": "uint256",
        "name": "amount",
        "type": "uint256"
      },
      {
        "indexed": true,
        "internalType": "bytes32",
        "name": "vegaPublicKey",
        "type": "bytes32"
      }
    ],
    "name": "StakeRemoved",
    "type": "event"
  },
  {
    "anonymous": false,
    "inputs": [
      {
        "indexed": true,
        "internalType": "address",
        "name": "from",
        "type": "address"
      },
      {
        "indexed": false,
        "internalType": "uint256",
        "name": "amount",
        "type": "uint256"
      },
      {
        "indexed": true,
        "internalType": "address",
        "name": "to",
        "type": "address"
      },
      {
        "indexed": true,
        "internalType": "bytes32",
        "name": "vegaPublicKey",
        "type": "bytes32"
      }
    ],
    "name": "StakeTransferred",
    "type": "event"
  },
  {
    "inputs": [
      {
        "internalType": "uint256",
        "name": "amount",
        "type": "uint256"
      },
      {
        "internalType": "bytes32",
        "name": "vegaPublicKey",
        "type": "bytes32"
      }
    ],
    "name": "removeStake",
    "outputs": [],
    "stateMutability": "nonpayable",
    "type": "function"
  },
  {
    "inputs": [
      {
        "internalType": "uint256",
        "name": "amount",
        "type": "uint256"
      },
      {
        "internalType": "bytes32",
        "name": "vegaPublicKey",
        "type": "bytes32"
      }
    ],
    "name": "stake",
    "outputs": [],
    "stateMutability": "nonpayable",
    "type": "function"
  },
  {
    "inputs": [
      {
        "internalType": "address",
        "name": "target",
        "type": "address"
      },
      {
        "internalType": "bytes32",
        "name": "vegaPublicKey",
        "type": "bytes32"
      }
    ],
    "name": "stakeBalance",
    "outputs": [
      {
        "internalType": "uint256",
        "name": "",
        "type": "uint256"
      }
    ],
    "stateMutability": "view",
    "type": "function"
  },
  {
    "inputs": [],
    "name": "stakingToken",
    "outputs": [
      {
        "internalType": "address",
        "name": "",
        "type": "address"
      }
    ],
    "stateMutability": "view",
    "type": "function"
  },
  {
    "inputs": [],
    "name": "totalStaked",
    "outputs": [
      {
        "internalType": "uint256",
        "name": "",
        "type": "uint256"
      }
    ],
    "stateMutability": "view",
    "type": "function"
  },
  {
    "inputs": [
      {
        "internalType": "uint256",
        "name": "amount",
        "type": "uint256"
      },
      {
        "internalType": "address",
        "name": "newAddress",
        "type": "address"
      },
      {
        "internalType": "bytes32",
        "name": "vegaPublicKey",
        "type": "bytes32"
      }
    ],
    "name": "transferStake",
    "outputs": [],
    "stateMutability": "nonpayable",
    "type": "function"
  }
]
